Metadata-Version: 2.1
Name: minimizers
Version: 0.1.0
Summary: A Python package for extracting minimizers from sequence data
Home-page: http://github.com/cumbof/minimizers
Author: Fabio Cumbo
Author-email: fabio.cumbo@gmail.com
License: MIT
Download-URL: https://pypi.org/project/minimizers/
Project-URL: Issues, https://github.com/cumbof/minimizers/issues
Project-URL: Source, https://github.com/cumbof/minimizers
Keywords: bioinformatics,minimizers,sketches
Platform: UNKNOWN
Classifier: Environment :: Console
Classifier: Intended Audience :: Science/Research
Classifier: License :: OSI Approved :: MIT License
Classifier: Natural Language :: English
Classifier: Programming Language :: Python :: 3
Classifier: Topic :: Scientific/Engineering :: Bio-Informatics
Requires-Python: >=3.6
